Workbook

Sheet How to fill
A1: SunoBro product sheet
A3: What this is | B3: One file for every product on www.sunobro.com. Fill it, upload it in admin → Products → Import, and the site updates.
A4: Products tab | B4: One row per product (e.g. 'Unisex Classic Crew T-Shirt'). Name, description, selling price, status and cover image.
A5: Variants tab | B5: One row per colour × size of that product. A tee in 3 colours × 4 sizes = 12 rows. Each row needs its Qikink Store SKU.
A6: Where the Store SKU comes from | B6: Qikink dashboard → My Products → the product → Product Variations → 'Store SKU' column (starts with v-…). NOT the 'Product SKU' (like MRnHs-Wh-M) — Qikink rejects that.
A7: Images | B7: Use public image links (Qikink mockup links work: right-click the mockup → Copy image address). Cover image on Products; one image per colour on Variants (same link on every size of that colour).
A8: Prices | B8: Selling price in ₹ on Products. Leave 'Price override' blank unless one size costs more (e.g. XXL ₹649).
A9: Status | B9: active = visible on the site (only if every variant has a Store SKU — see 'Ready to publish'). draft = saved but hidden.
A10: Updating later | B10: Re-upload the same sheet after edits. Products are matched by Product name; variants by colour + size. Remove a row to remove that variant.
A12: Colour key
A13: Yellow cells | B13: Required — you fill these.
A14: Light yellow cells | B14: Optional — fill if you need them.
A15: Grey cells | B15: Calculated automatically — don't type here.
A16: Blue text | B16: Values you entered. Black text = formulas.
A18: Example | B18: The rows already filled in are the live 'Unisex Classic Crew T-Shirt' (12 variants, real Store SKUs, ₹599). Keep them or overwrite them.

Sheet Products
A1: Product name * | B1: Description * | C1: Selling price ₹ * | D1: Status * | E1: Cover image URL * | F1: More image URLs (separate with |) | G1: URL slug (auto if blank) | H1: Qikink Product ID | I1: Design name | J1: Print size (W × H in) | K1: Variants | L1: With Store SKU | M1: Ready to publish
A2: Unisex Classic Crew T-Shirt | B2: Classic crew-neck cotton tee with the SunoBro print. Printed on demand and shipped across India. | C2: 599 | D2: active | E2: https://qikink-assets.s3.ap-south-1.amazonaws.com/clients/621544/clientProducts/32422268/images/Front_1_c_1.jpg | G2: unisex-classic-crew-t-shirt | H2: 64844536 | I2: imgtext | J2: 14 × 6.4 | K2: =IF(A2="","",COUNTIF(Variants!$A:$A,A2)) | L2: =IF(A2="","",COUNTIFS(Variants!$A:$A,A2,Variants!$D:$D,"<>")) | M2: =IF(A2="","",IF(K2=0,"ADD VARIANTS",IF(L2<K2,"MISSING "&(K2-L2)&" STORE SKU",IF(E2="","ADD COVER IMAGE","READY"))))
K3: =IF(A3="","",COUNTIF(Variants!$A:$A,A3)) | L3: =IF(A3="","",COUNTIFS(Variants!$A:$A,A3,Variants!$D:$D,"<>")) | M3: =IF(A3="","",IF(K3=0,"ADD VARIANTS",IF(L3<K3,"MISSING "&(K3-L3)&" STORE SKU",IF(E3="","ADD COVER IMAGE","READY"))))
K4: =IF(A4="","",COUNTIF(Variants!$A:$A,A4)) | L4: =IF(A4="","",COUNTIFS(Variants!$A:$A,A4,Variants!$D:$D,"<>")) | M4: =IF(A4="","",IF(K4=0,"ADD VARIANTS",IF(L4<K4,"MISSING "&(K4-L4)&" STORE SKU",IF(E4="","ADD COVER IMAGE","READY"))))
K5: =IF(A5="","",COUNTIF(Variants!$A:$A,A5)) | L5: =IF(A5="","",COUNTIFS(Variants!$A:$A,A5,Variants!$D:$D,"<>")) | M5: =IF(A5="","",IF(K5=0,"ADD VARIANTS",IF(L5<K5,"MISSING "&(K5-L5)&" STORE SKU",IF(E5="","ADD COVER IMAGE","READY"))))
K6: =IF(A6="","",COUNTIF(Variants!$A:$A,A6)) | L6: =IF(A6="","",COUNTIFS(Variants!$A:$A,A6,Variants!$D:$D,"<>")) | M6: =IF(A6="","",IF(K6=0,"ADD VARIANTS",IF(L6<K6,"MISSING "&(K6-L6)&" STORE SKU",IF(E6="","ADD COVER IMAGE","READY"))))
K7: =IF(A7="","",COUNTIF(Variants!$A:$A,A7)) | L7: =IF(A7="","",COUNTIFS(Variants!$A:$A,A7,Variants!$D:$D,"<>")) | M7: =IF(A7="","",IF(K7=0,"ADD VARIANTS",IF(L7<K7,"MISSING "&(K7-L7)&" STORE SKU",IF(E7="","ADD COVER IMAGE","READY"))))
K8: =IF(A8="","",COUNTIF(Variants!$A:$A,A8)) | L8: =IF(A8="","",COUNTIFS(Variants!$A:$A,A8,Variants!$D:$D,"<>")) | M8: =IF(A8="","",IF(K8=0,"ADD VARIANTS",IF(L8<K8,"MISSING "&(K8-L8)&" STORE SKU",IF(E8="","ADD COVER IMAGE","READY"))))
K9: =IF(A9="","",COUNTIF(Variants!$A:$A,A9)) | L9: =IF(A9="","",COUNTIFS(Variants!$A:$A,A9,Variants!$D:$D,"<>")) | M9: =IF(A9="","",IF(K9=0,"ADD VARIANTS",IF(L9<K9,"MISSING "&(K9-L9)&" STORE SKU",IF(E9="","ADD COVER IMAGE","READY"))))
K10: =IF(A10="","",COUNTIF(Variants!$A:$A,A10)) | L10: =IF(A10="","",COUNTIFS(Variants!$A:$A,A10,Variants!$D:$D,"<>")) | M10: =IF(A10="","",IF(K10=0,"ADD VARIANTS",IF(L10<K10,"MISSING "&(K10-L10)&" STORE SKU",IF(E10="","ADD COVER IMAGE","READY"))))
K11: =IF(A11="","",COUNTIF(Variants!$A:$A,A11)) | L11: =IF(A11="","",COUNTIFS(Variants!$A:$A,A11,Variants!$D:$D,"<>")) | M11: =IF(A11="","",IF(K11=0,"ADD VARIANTS",IF(L11<K11,"MISSING "&(K11-L11)&" STORE SKU",IF(E11="","ADD COVER IMAGE","READY"))))
K12: =IF(A12="","",COUNTIF(Variants!$A:$A,A12)) | L12: =IF(A12="","",COUNTIFS(Variants!$A:$A,A12,Variants!$D:$D,"<>")) | M12: =IF(A12="","",IF(K12=0,"ADD VARIANTS",IF(L12<K12,"MISSING "&(K12-L12)&" STORE SKU",IF(E12="","ADD COVER IMAGE","READY"))))
K13: =IF(A13="","",COUNTIF(Variants!$A:$A,A13)) | L13: =IF(A13="","",COUNTIFS(Variants!$A:$A,A13,Variants!$D:$D,"<>")) | M13: =IF(A13="","",IF(K13=0,"ADD VARIANTS",IF(L13<K13,"MISSING "&(K13-L13)&" STORE SKU",IF(E13="","ADD COVER IMAGE","READY"))))
K14: =IF(A14="","",COUNTIF(Variants!$A:$A,A14)) | L14: =IF(A14="","",COUNTIFS(Variants!$A:$A,A14,Variants!$D:$D,"<>")) | M14: =IF(A14="","",IF(K14=0,"ADD VARIANTS",IF(L14<K14,"MISSING "&(K14-L14)&" STORE SKU",IF(E14="","ADD COVER IMAGE","READY"))))
... K60: =IF(A60="","",COUNTIF(Variants!$A:$A,A60)) | L60: =IF(A60="","",COUNTIFS(Variants!$A:$A,A60,Variants!$D:$D,"<>")) | M60: =IF(A60="","",IF(K60=0,"ADD VARIANTS",IF(L60<K60,"MISSING "&(K60-L60)&" STORE SKU",IF(E60="","ADD COVER IMAGE","READY"))))

Sheet Variants
A1: Product name * | B1: Colour * | C1: Size * | D1: Qikink Store SKU * (v-…) | E1: Colour image URL | F1: Price override ₹ | G1: Qikink Product SKU (reference) | H1: Qikink cost ₹ | I1: Final price ₹ | J1: Margin ₹ | K1: Check
A2: Unisex Classic Crew T-Shirt | B2: White | C2: M | D2: v-9Rqh0iKDaVZW18UNNhEhubTepA3d8nuc | E2: https://qikink-assets.s3.ap-south-1.amazonaws.com/clients/621544/clientProducts/32422268/images/Front_1_c_1.jpg | G2: MRnHs-Wh-M | H2: 252 | I2: =IF(A2="","",IF(F2<>"",F2,IFERROR(INDEX(Products!$C:$C,MATCH(A2,Products!$A:$A,0)),""))) | J2: =IF(OR(I2="",H2=""),"",I2-H2) | K2: =IF(A2="","",IF(ISNA(MATCH(A2,Products!$A:$A,0)),"NAME NOT IN PRODUCTS",IF(D2="","ADD STORE SKU",IF(LEFT(D2,2)<>"v-","CHECK: STORE SKU STARTS WITH v-",IF(COUNTIF($D:$D,D2)>1,"DUPLICATE STORE SKU",IF(COUNTIFS($A:$A,A2,$B:$B,B2,$C:$C,C2)>1,"DUPLICATE COLOUR + SIZE","OK"))))))
A3: Unisex Classic Crew T-Shirt | B3: White | C3: L | D3: v-9Rqh0iKDaVZW18UNNhEhubTepA3d8nud | E3: https://qikink-assets.s3.ap-south-1.amazonaws.com/clients/621544/clientProducts/32422268/images/Front_1_c_1.jpg | G3: MRnHs-Wh-L | H3: 252 | I3: =IF(A3="","",IF(F3<>"",F3,IFERROR(INDEX(Products!$C:$C,MATCH(A3,Products!$A:$A,0)),""))) | J3: =IF(OR(I3="",H3=""),"",I3-H3) | K3: =IF(A3="","",IF(ISNA(MATCH(A3,Products!$A:$A,0)),"NAME NOT IN PRODUCTS",IF(D3="","ADD STORE SKU",IF(LEFT(D3,2)<>"v-","CHECK: STORE SKU STARTS WITH v-",IF(COUNTIF($D:$D,D3)>1,"DUPLICATE STORE SKU",IF(COUNTIFS($A:$A,A3,$B:$B,B3,$C:$C,C3)>1,"DUPLICATE COLOUR + SIZE","OK"))))))
A4: Unisex Classic Crew T-Shirt | B4: White | C4: XL | D4: v-9Rqh0iKDaVZW18UNNhEhubTepA3d8nue | E4: https://qikink-assets.s3.ap-south-1.amazonaws.com/clients/621544/clientProducts/32422268/images/Front_1_c_1.jpg | G4: MRnHs-Wh-XL | H4: 252 | I4: =IF(A4="","",IF(F4<>"",F4,IFERROR(INDEX(Products!$C:$C,MATCH(A4,Products!$A:$A,0)),""))) | J4: =IF(OR(I4="",H4=""),"",I4-H4) | K4: =IF(A4="","",IF(ISNA(MATCH(A4,Products!$A:$A,0)),"NAME NOT IN PRODUCTS",IF(D4="","ADD STORE SKU",IF(LEFT(D4,2)<>"v-","CHECK: STORE SKU STARTS WITH v-",IF(COUNTIF($D:$D,D4)>1,"DUPLICATE STORE SKU",IF(COUNTIFS($A:$A,A4,$B:$B,B4,$C:$C,C4)>1,"DUPLICATE COLOUR + SIZE","OK"))))))
A5: Unisex Classic Crew T-Shirt | B5: White | C5: XXL | D5: v-9Rqh0iKDaVZW18UNNhEhubTepA3d8nuf | E5: https://qikink-assets.s3.ap-south-1.amazonaws.com/clients/621544/clientProducts/32422268/images/Front_1_c_1.jpg | G5: MRnHs-Wh-XXL | H5: 252 | I5: =IF(A5="","",IF(F5<>"",F5,IFERROR(INDEX(Products!$C:$C,MATCH(A5,Products!$A:$A,0)),""))) | J5: =IF(OR(I5="",H5=""),"",I5-H5) | K5: =IF(A5="","",IF(ISNA(MATCH(A5,Products!$A:$A,0)),"NAME NOT IN PRODUCTS",IF(D5="","ADD STORE SKU",IF(LEFT(D5,2)<>"v-","CHECK: STORE SKU STARTS WITH v-",IF(COUNTIF($D:$D,D5)>1,"DUPLICATE STORE SKU",IF(COUNTIFS($A:$A,A5,$B:$B,B5,$C:$C,C5)>1,"DUPLICATE COLOUR + SIZE","OK"))))))
A6: Unisex Classic Crew T-Shirt | B6: Navy Blue | C6: M | D6: v-9Rqh0iKDaVZW18UNNhEhubTepA3d8nuY | G6: MRnHs-Nb-M | H6: 304.5 | I6: =IF(A6="","",IF(F6<>"",F6,IFERROR(INDEX(Products!$C:$C,MATCH(A6,Products!$A:$A,0)),""))) | J6: =IF(OR(I6="",H6=""),"",I6-H6) | K6: =IF(A6="","",IF(ISNA(MATCH(A6,Products!$A:$A,0)),"NAME NOT IN PRODUCTS",IF(D6="","ADD STORE SKU",IF(LEFT(D6,2)<>"v-","CHECK: STORE SKU STARTS WITH v-",IF(COUNTIF($D:$D,D6)>1,"DUPLICATE STORE SKU",IF(COUNTIFS($A:$A,A6,$B:$B,B6,$C:$C,C6)>1,"DUPLICATE COLOUR + SIZE","OK"))))))
A7: Unisex Classic Crew T-Shirt | B7: Navy Blue | C7: L | D7: v-9Rqh0iKDaVZW18UNNhEhubTepA3d8nuZ | G7: MRnHs-Nb-L | H7: 304.5 | I7: =IF(A7="","",IF(F7<>"",F7,IFERROR(INDEX(Products!$C:$C,MATCH(A7,Products!$A:$A,0)),""))) | J7: =IF(OR(I7="",H7=""),"",I7-H7) | K7: =IF(A7="","",IF(ISNA(MATCH(A7,Products!$A:$A,0)),"NAME NOT IN PRODUCTS",IF(D7="","ADD STORE SKU",IF(LEFT(D7,2)<>"v-","CHECK: STORE SKU STARTS WITH v-",IF(COUNTIF($D:$D,D7)>1,"DUPLICATE STORE SKU",IF(COUNTIFS($A:$A,A7,$B:$B,B7,$C:$C,C7)>1,"DUPLICATE COLOUR + SIZE","OK"))))))
A8: Unisex Classic Crew T-Shirt | B8: Navy Blue | C8: XL | D8: v-9Rqh0iKDaVZW18UNNhEhubTepA3d8nua | G8: MRnHs-Nb-XL | H8: 304.5 | I8: =IF(A8="","",IF(F8<>"",F8,IFERROR(INDEX(Products!$C:$C,MATCH(A8,Products!$A:$A,0)),""))) | J8: =IF(OR(I8="",H8=""),"",I8-H8) | K8: =IF(A8="","",IF(ISNA(MATCH(A8,Products!$A:$A,0)),"NAME NOT IN PRODUCTS",IF(D8="","ADD STORE SKU",IF(LEFT(D8,2)<>"v-","CHECK: STORE SKU STARTS WITH v-",IF(COUNTIF($D:$D,D8)>1,"DUPLICATE STORE SKU",IF(COUNTIFS($A:$A,A8,$B:$B,B8,$C:$C,C8)>1,"DUPLICATE COLOUR + SIZE","OK"))))))
A9: Unisex Classic Crew T-Shirt | B9: Navy Blue | C9: XXL | D9: v-9Rqh0iKDaVZW18UNNhEhubTepA3d8nub | G9: MRnHs-Nb-XXL | H9: 304.5 | I9: =IF(A9="","",IF(F9<>"",F9,IFERROR(INDEX(Products!$C:$C,MATCH(A9,Products!$A:$A,0)),""))) | J9: =IF(OR(I9="",H9=""),"",I9-H9) | K9: =IF(A9="","",IF(ISNA(MATCH(A9,Products!$A:$A,0)),"NAME NOT IN PRODUCTS",IF(D9="","ADD STORE SKU",IF(LEFT(D9,2)<>"v-","CHECK: STORE SKU STARTS WITH v-",IF(COUNTIF($D:$D,D9)>1,"DUPLICATE STORE SKU",IF(COUNTIFS($A:$A,A9,$B:$B,B9,$C:$C,C9)>1,"DUPLICATE COLOUR + SIZE","OK"))))))
A10: Unisex Classic Crew T-Shirt | B10: Grey Melange | C10: M | D10: v-9Rqh0iKDaVZW18UNNhEhubTepA3d8nuU | G10: MRnHs-Gm-M | H10: 304.5 | I10: =IF(A10="","",IF(F10<>"",F10,IFERROR(INDEX(Products!$C:$C,MATCH(A10,Products!$A:$A,0)),""))) | J10: =IF(OR(I10="",H10=""),"",I10-H10) | K10: =IF(A10="","",IF(ISNA(MATCH(A10,Products!$A:$A,0)),"NAME NOT IN PRODUCTS",IF(D10="","ADD STORE SKU",IF(LEFT(D10,2)<>"v-","CHECK: STORE SKU STARTS WITH v-",IF(COUNTIF($D:$D,D10)>1,"DUPLICATE STORE SKU",IF(COUNTIFS($A:$A,A10,$B:$B,B10,$C:$C,C10)>1,"DUPLICATE COLOUR + SIZE","OK"))))))
A11: Unisex Classic Crew T-Shirt | B11: Grey Melange | C11: L | D11: v-9Rqh0iKDaVZW18UNNhEhubTepA3d8nuV | G11: MRnHs-Gm-L | H11: 304.5 | I11: =IF(A11="","",IF(F11<>"",F11,IFERROR(INDEX(Products!$C:$C,MATCH(A11,Products!$A:$A,0)),""))) | J11: =IF(OR(I11="",H11=""),"",I11-H11) | K11: =IF(A11="","",IF(ISNA(MATCH(A11,Products!$A:$A,0)),"NAME NOT IN PRODUCTS",IF(D11="","ADD STORE SKU",IF(LEFT(D11,2)<>"v-","CHECK: STORE SKU STARTS WITH v-",IF(COUNTIF($D:$D,D11)>1,"DUPLICATE STORE SKU",IF(COUNTIFS($A:$A,A11,$B:$B,B11,$C:$C,C11)>1,"DUPLICATE COLOUR + SIZE","OK"))))))
A12: Unisex Classic Crew T-Shirt | B12: Grey Melange | C12: XL | D12: v-9Rqh0iKDaVZW18UNNhEhubTepA3d9XKc | G12: MRnHs-Gm-XL | H12: 304.5 | I12: =IF(A12="","",IF(F12<>"",F12,IFERROR(INDEX(Products!$C:$C,MATCH(A12,Products!$A:$A,0)),""))) | J12: =IF(OR(I12="",H12=""),"",I12-H12) | K12: =IF(A12="","",IF(ISNA(MATCH(A12,Products!$A:$A,0)),"NAME NOT IN PRODUCTS",IF(D12="","ADD STORE SKU",IF(LEFT(D12,2)<>"v-","CHECK: STORE SKU STARTS WITH v-",IF(COUNTIF($D:$D,D12)>1,"DUPLICATE STORE SKU",IF(COUNTIFS($A:$A,A12,$B:$B,B12,$C:$C,C12)>1,"DUPLICATE COLOUR + SIZE","OK"))))))
A13: Unisex Classic Crew T-Shirt | B13: Grey Melange | C13: XXL | D13: v-9Rqh0iKDaVZW18UNNhEhubTepA3d9XKd | G13: MRnHs-Gm-XXL | H13: 304.5 | I13: =IF(A13="","",IF(F13<>"",F13,IFERROR(INDEX(Products!$C:$C,MATCH(A13,Products!$A:$A,0)),""))) | J13: =IF(OR(I13="",H13=""),"",I13-H13) | K13: =IF(A13="","",IF(ISNA(MATCH(A13,Products!$A:$A,0)),"NAME NOT IN PRODUCTS",IF(D13="","ADD STORE SKU",IF(LEFT(D13,2)<>"v-","CHECK: STORE SKU STARTS WITH v-",IF(COUNTIF($D:$D,D13)>1,"DUPLICATE STORE SKU",IF(COUNTIFS($A:$A,A13,$B:$B,B13,$C:$C,C13)>1,"DUPLICATE COLOUR + SIZE","OK"))))))
I14: =IF(A14="","",IF(F14<>"",F14,IFERROR(INDEX(Products!$C:$C,MATCH(A14,Products!$A:$A,0)),""))) | J14: =IF(OR(I14="",H14=""),"",I14-H14) | K14: =IF(A14="","",IF(ISNA(MATCH(A14,Products!$A:$A,0)),"NAME NOT IN PRODUCTS",IF(D14="","ADD STORE SKU",IF(LEFT(D14,2)<>"v-","CHECK: STORE SKU STARTS WITH v-",IF(COUNTIF($D:$D,D14)>1,"DUPLICATE STORE SKU",IF(COUNTIFS($A:$A,A14,$B:$B,B14,$C:$C,C14)>1,"DUPLICATE COLOUR + SIZE","OK"))))))
I15: =IF(A15="","",IF(F15<>"",F15,IFERROR(INDEX(Products!$C:$C,MATCH(A15,Products!$A:$A,0)),""))) | J15: =IF(OR(I15="",H15=""),"",I15-H15) | K15: =IF(A15="","",IF(ISNA(MATCH(A15,Products!$A:$A,0)),"NAME NOT IN PRODUCTS",IF(D15="","ADD STORE SKU",IF(LEFT(D15,2)<>"v-","CHECK: STORE SKU STARTS WITH v-",IF(COUNTIF($D:$D,D15)>1,"DUPLICATE STORE SKU",IF(COUNTIFS($A:$A,A15,$B:$B,B15,$C:$C,C15)>1,"DUPLICATE COLOUR + SIZE","OK"))))))
I16: =IF(A16="","",IF(F16<>"",F16,IFERROR(INDEX(Products!$C:$C,MATCH(A16,Products!$A:$A,0)),""))) | J16: =IF(OR(I16="",H16=""),"",I16-H16) | K16: =IF(A16="","",IF(ISNA(MATCH(A16,Products!$A:$A,0)),"NAME NOT IN PRODUCTS",IF(D16="","ADD STORE SKU",IF(LEFT(D16,2)<>"v-","CHECK: STORE SKU STARTS WITH v-",IF(COUNTIF($D:$D,D16)>1,"DUPLICATE STORE SKU",IF(COUNTIFS($A:$A,A16,$B:$B,B16,$C:$C,C16)>1,"DUPLICATE COLOUR + SIZE","OK"))))))
I17: =IF(A17="","",IF(F17<>"",F17,IFERROR(INDEX(Products!$C:$C,MATCH(A17,Products!$A:$A,0)),""))) | J17: =IF(OR(I17="",H17=""),"",I17-H17) | K17: =IF(A17="","",IF(ISNA(MATCH(A17,Products!$A:$A,0)),"NAME NOT IN PRODUCTS",IF(D17="","ADD STORE SKU",IF(LEFT(D17,2)<>"v-","CHECK: STORE SKU STARTS WITH v-",IF(COUNTIF($D:$D,D17)>1,"DUPLICATE STORE SKU",IF(COUNTIFS($A:$A,A17,$B:$B,B17,$C:$C,C17)>1,"DUPLICATE COLOUR + SIZE","OK"))))))
I18: =IF(A18="","",IF(F18<>"",F18,IFERROR(INDEX(Products!$C:$C,MATCH(A18,Products!$A:$A,0)),""))) | J18: =IF(OR(I18="",H18=""),"",I18-H18) | K18: =IF(A18="","",IF(ISNA(MATCH(A18,Products!$A:$A,0)),"NAME NOT IN PRODUCTS",IF(D18="","ADD STORE SKU",IF(LEFT(D18,2)<>"v-","CHECK: STORE SKU STARTS WITH v-",IF(COUNTIF($D:$D,D18)>1,"DUPLICATE STORE SKU",IF(COUNTIFS($A:$A,A18,$B:$B,B18,$C:$C,C18)>1,"DUPLICATE COLOUR + SIZE","OK"))))))
I19: =IF(A19="","",IF(F19<>"",F19,IFERROR(INDEX(Products!$C:$C,MATCH(A19,Products!$A:$A,0)),""))) | J19: =IF(OR(I19="",H19=""),"",I19-H19) | K19: =IF(A19="","",IF(ISNA(MATCH(A19,Products!$A:$A,0)),"NAME NOT IN PRODUCTS",IF(D19="","ADD STORE SKU",IF(LEFT(D19,2)<>"v-","CHECK: STORE SKU STARTS WITH v-",IF(COUNTIF($D:$D,D19)>1,"DUPLICATE STORE SKU",IF(COUNTIFS($A:$A,A19,$B:$B,B19,$C:$C,C19)>1,"DUPLICATE COLOUR + SIZE","OK"))))))
I20: =IF(A20="","",IF(F20<>"",F20,IFERROR(INDEX(Products!$C:$C,MATCH(A20,Products!$A:$A,0)),""))) | J20: =IF(OR(I20="",H20=""),"",I20-H20) | K20: =IF(A20="","",IF(ISNA(MATCH(A20,Products!$A:$A,0)),"NAME NOT IN PRODUCTS",IF(D20="","ADD STORE SKU",IF(LEFT(D20,2)<>"v-","CHECK: STORE SKU STARTS WITH v-",IF(COUNTIF($D:$D,D20)>1,"DUPLICATE STORE SKU",IF(COUNTIFS($A:$A,A20,$B:$B,B20,$C:$C,C20)>1,"DUPLICATE COLOUR + SIZE","OK"))))))
I21: =IF(A21="","",IF(F21<>"",F21,IFERROR(INDEX(Products!$C:$C,MATCH(A21,Products!$A:$A,0)),""))) | J21: =IF(OR(I21="",H21=""),"",I21-H21) | K21: =IF(A21="","",IF(ISNA(MATCH(A21,Products!$A:$A,0)),"NAME NOT IN PRODUCTS",IF(D21="","ADD STORE SKU",IF(LEFT(D21,2)<>"v-","CHECK: STORE SKU STARTS WITH v-",IF(COUNTIF($D:$D,D21)>1,"DUPLICATE STORE SKU",IF(COUNTIFS($A:$A,A21,$B:$B,B21,$C:$C,C21)>1,"DUPLICATE COLOUR + SIZE","OK"))))))
I22: =IF(A22="","",IF(F22<>"",F22,IFERROR(INDEX(Products!$C:$C,MATCH(A22,Products!$A:$A,0)),""))) | J22: =IF(OR(I22="",H22=""),"",I22-H22) | K22: =IF(A22="","",IF(ISNA(MATCH(A22,Products!$A:$A,0)),"NAME NOT IN PRODUCTS",IF(D22="","ADD STORE SKU",IF(LEFT(D22,2)<>"v-","CHECK: STORE SKU STARTS WITH v-",IF(COUNTIF($D:$D,D22)>1,"DUPLICATE STORE SKU",IF(COUNTIFS($A:$A,A22,$B:$B,B22,$C:$C,C22)>1,"DUPLICATE COLOUR + SIZE","OK"))))))
I23: =IF(A23="","",IF(F23<>"",F23,IFERROR(INDEX(Products!$C:$C,MATCH(A23,Products!$A:$A,0)),""))) | J23: =IF(OR(I23="",H23=""),"",I23-H23) | K23: =IF(A23="","",IF(ISNA(MATCH(A23,Products!$A:$A,0)),"NAME NOT IN PRODUCTS",IF(D23="","ADD STORE SKU",IF(LEFT(D23,2)<>"v-","CHECK: STORE SKU STARTS WITH v-",IF(COUNTIF($D:$D,D23)>1,"DUPLICATE STORE SKU",IF(COUNTIFS($A:$A,A23,$B:$B,B23,$C:$C,C23)>1,"DUPLICATE COLOUR + SIZE","OK"))))))
I24: =IF(A24="","",IF(F24<>"",F24,IFERROR(INDEX(Products!$C:$C,MATCH(A24,Products!$A:$A,0)),""))) | J24: =IF(OR(I24="",H24=""),"",I24-H24) | K24: =IF(A24="","",IF(ISNA(MATCH(A24,Products!$A:$A,0)),"NAME NOT IN PRODUCTS",IF(D24="","ADD STORE SKU",IF(LEFT(D24,2)<>"v-","CHECK: STORE SKU STARTS WITH v-",IF(COUNTIF($D:$D,D24)>1,"DUPLICATE STORE SKU",IF(COUNTIFS($A:$A,A24,$B:$B,B24,$C:$C,C24)>1,"DUPLICATE COLOUR + SIZE","OK"))))))
I25: =IF(A25="","",IF(F25<>"",F25,IFERROR(INDEX(Products!$C:$C,MATCH(A25,Products!$A:$A,0)),""))) | J25: =IF(OR(I25="",H25=""),"",I25-H25) | K25: =IF(A25="","",IF(ISNA(MATCH(A25,Products!$A:$A,0)),"NAME NOT IN PRODUCTS",IF(D25="","ADD STORE SKU",IF(LEFT(D25,2)<>"v-","CHECK: STORE SKU STARTS WITH v-",IF(COUNTIF($D:$D,D25)>1,"DUPLICATE STORE SKU",IF(COUNTIFS($A:$A,A25,$B:$B,B25,$C:$C,C25)>1,"DUPLICATE COLOUR + SIZE","OK"))))))
... I600: =IF(A600="","",IF(F600<>"",F600,IFERROR(INDEX(Products!$C:$C,MATCH(A600,Products!$A:$A,0)),""))) | J600: =IF(OR(I600="",H600=""),"",I600-H600) | K600: =IF(A600="","",IF(ISNA(MATCH(A600,Products!$A:$A,0)),"NAME NOT IN PRODUCTS",IF(D600="","ADD STORE SKU",IF(LEFT(D600,2)<>"v-","CHECK: STORE SKU STARTS WITH v-",IF(COUNTIF($D:$D,D600)>1,"DUPLICATE STORE SKU",IF(COUNTIFS($A:$A,A600,$B:$B,B600,$C:$C,C600)>1,"DUPLICATE COLOUR + SIZE","OK"))))))

Sheet Lists
A1: Sizes | B1: Statuses | C1: Common colours (you can type others)
A2: XS | B2: active | C2: White
A3: S | B3: draft | C3: Black
A4: M | C4: Navy Blue
A5: L | C5: Grey Melange
A6: XL | C6: Maroon
A7: XXL | C7: Bottle Green
A8: 3XL | C8: Royal Blue
A9: 4XL | C9: Red
A10: 5XL | C10: Yellow
A11: Free Size | C11: Olive Green
C12: Beige
C13: Lavender
C14: Baby Pink
C15: Sky Blue
C16: Charcoal Melange
